polvo/__init__.py
polvo/_modidx.py
polvo/test.py
polvo/bbox/__init__.py
polvo/bbox/core.py
polvo/bbox/vis.py
polvo/classification/__init__.py
polvo/classification/explorer.py
polvo/classification/baseline/__init__.py
polvo/classification/baseline/baseline.py
polvo/converter/__init__.py
polvo/converter/coco.py
polvo/converter/yolo.py
polvo/data/__init__.py
polvo/data/core.py
polvo/data/transforms.py
polvo/datasets/__init__.py
polvo/datasets/download.py
polvo/draw/__init__.py
polvo/draw/pil_drawer.py
polvo/keypoint/__init__.py
polvo/keypoint/core.py
polvo/keypoint/vis.py
polvo/segmask/__init__.py
polvo/segmask/core.py
polvo/segmask/vis.py
polvo/segmentation/__init__.py
polvo/segmentation/vis.py
polvo/utils/__init__.py
polvo/utils/download.py
polvo/utils/image_size.py
polvo/utils/io.py
polvo/utils/logging.py
polvo/utils/misc.py
polvo/utils/script.py
polvo/utils/splits.py
polvo/utils/visualization.py
polvo/utils/wandb.py
polvo/visitor/__init__.py
polvo/visitor/core.py
polvo-0.2.5.dist-info/LICENSE
polvo-0.2.5.dist-info/METADATA
polvo-0.2.5.dist-info/WHEEL
polvo-0.2.5.dist-info/entry_points.txt
polvo-0.2.5.dist-info/top_level.txt
polvo-0.2.5.dist-info/RECORD
