Metadata-Version: 2.1
Name: polvo
Version: 0.2.5
Summary: A collection of computer vision tools that fits anywhere
Home-page: https://github.com/lgvaz/polvo/
Author: lgvaz
Author-email: lgvaz42@gmail.com
License: Apache Software License 2.0
Keywords: computer-vision deep-learning fastai
Classifier: Development Status :: 3 - Alpha
Classifier: Intended Audience :: Developers
Classifier: Natural Language :: English
Classifier: Programming Language :: Python :: 3.7
Classifier: Programming Language :: Python :: 3.8
Classifier: Programming Language :: Python :: 3.9
Classifier: Programming Language :: Python :: 3.10
Classifier: License :: OSI Approved :: Apache Software License
Requires-Python: >=3.7
License-File: LICENSE
Requires-Dist: fastcore
Requires-Dist: nbdev (>=0.2.3)
Requires-Dist: tqdm
Requires-Dist: numpy
Requires-Dist: matplotlib
Requires-Dist: pandas
Provides-Extra: dev
Requires-Dist: requests ; extra == 'dev'
